{
  "text": "哆啦A梦",
  "fontName": "Arial",
  "fontSize": 24,
  "bold": true,
  "italic": false,
  "color": "#ff0000",
  "opacity": 100.0,
  "imageScale": 100.0,
  "imageOpacity": 100.0,
  "position": "BOTTOM_RIGHT",
  "rotation": -36.0,
  "x": 0.0,
  "y": 0.0,
  "edgePadding": 20.0,
  "exportFormat": "PNG",
  "jpegQuality": 90.0,
  "namingConvention": "ORIGINAL",
  "prefix": "",
  "suffix": "_watermarked",
  "resizeEnabled": false,
  "resizeWidth": 800.0,
  "resizeHeight": 600.0,
  "resizePercentage": 100.0
}